pynumic/__init__.py
pynumic/__version__.py
pynumic/py.typed
pynumic/pynumic.py
pynumic-0.1.0.dist-info/LICENSE
pynumic-0.1.0.dist-info/METADATA
pynumic-0.1.0.dist-info/WHEEL
pynumic-0.1.0.dist-info/RECORD
